infer_compiler_registry/__init__.py
infer_compiler_registry/register_diffusers/__init__.py
infer_compiler_registry/register_diffusers/attention_processor_oflow.py
infer_compiler_registry/register_diffusers/resnet_oflow.py
infer_compiler_registry/register_diffusers/spatio_temporal_oflow.py
infer_compiler_registry/register_diffusers/transformer_2d_oflow.py
infer_compiler_registry/register_diffusers/unet_2d_blocks_oflow.py
infer_compiler_registry/register_diffusers/unet_2d_condition_oflow.py
infer_compiler_registry/register_diffusers/transformer_2d/__init__.py
infer_compiler_registry/register_diffusers/transformer_2d/v_0_28.py
infer_compiler_registry/register_diffusers_enterprise_lite/__init__.py
infer_compiler_registry/register_onediff_quant/__init__.py
onediff/__init__.py
onediff/_version.py
onediff/infer_compiler/__init__.py
onediff/infer_compiler/backends/__init__.py
onediff/infer_compiler/backends/compiler.py
onediff/infer_compiler/backends/deployable_module.py
onediff/infer_compiler/backends/env_var.py
onediff/infer_compiler/backends/registry.py
onediff/infer_compiler/backends/nexfort/__init__.py
onediff/infer_compiler/backends/nexfort/deployable_module.py
onediff/infer_compiler/backends/nexfort/nexfort.py
onediff/infer_compiler/backends/oneflow/__init__.py
onediff/infer_compiler/backends/oneflow/args_tree_util.py
onediff/infer_compiler/backends/oneflow/deployable_module.py
onediff/infer_compiler/backends/oneflow/dual_module.py
onediff/infer_compiler/backends/oneflow/graph.py
onediff/infer_compiler/backends/oneflow/graph_management_utils.py
onediff/infer_compiler/backends/oneflow/oneflow.py
onediff/infer_compiler/backends/oneflow/oneflow_exec_mode.py
onediff/infer_compiler/backends/oneflow/online_quantization_utils.py
onediff/infer_compiler/backends/oneflow/param_utils.py
onediff/infer_compiler/backends/oneflow/import_tools/__init__.py
onediff/infer_compiler/backends/oneflow/import_tools/dyn_mock_mod.py
onediff-1.2.0.dist-info/LICENSE
onediff-1.2.0.dist-info/METADATA
onediff-1.2.0.dist-info/WHEEL
onediff-1.2.0.dist-info/top_level.txt
onediff-1.2.0.dist-info/RECORD
