Metadata-Version: 2.1
Name: onediff
Version: 1.2.0
Summary: an out-of-the-box acceleration library for diffusion models
Home-page: https://github.com/siliconflow/onediff
Author: OneDiff contributors
Author-email: contact@siliconflow.com
License: Apache-2.0
Classifier: Development Status :: 5 - Production/Stable
Classifier: Intended Audience :: Developers
Classifier: Intended Audience :: Education
Classifier: Intended Audience :: Science/Research
Classifier: License :: OSI Approved :: Apache Software License
Classifier: Operating System :: OS Independent
Classifier: Programming Language :: Python :: 3
Classifier: Programming Language :: Python :: 3.8
Classifier: Programming Language :: Python :: 3.9
Classifier: Programming Language :: Python :: 3.10
Classifier: Topic :: Scientific/Engineering :: Artificial Intelligence
Requires-Python: >=3.8.0
License-File: LICENSE
Requires-Dist: transformers >=4.27.1
Requires-Dist: diffusers >=0.19.3
Requires-Dist: accelerate
Requires-Dist: torch
Provides-Extra: dev
Requires-Dist: pre-commit ; extra == 'dev'
